LxmlSoup/LxmlSoup.py
LxmlSoup/__init__.py
LxmlSoup/setup.py
LxmlSoup-1.5.2.dist-info/LICENSE
LxmlSoup-1.5.2.dist-info/METADATA
LxmlSoup-1.5.2.dist-info/WHEEL
LxmlSoup-1.5.2.dist-info/top_level.txt
LxmlSoup-1.5.2.dist-info/RECORD
