Metadata-Version: 2.1
Name: LxmlSoup
Version: 1.5.2
Summary: LxmlSoup is a set of tools for fast and easy parsing
Author: Alexander554
Author-email: gaa.280811@gmail.com
Keywords: LxmlSoup,BeautifulSoup,bs4,lxml,Soup
Classifier: Programming Language :: Python :: 3.11
Classifier: License :: OSI Approved :: MIT License
Classifier: Operating System :: OS Independent
Requires-Python: >=3.7
License-File: LICENSE
